headjack/__init__.py
headjack/api/__init__.py
headjack/api/app.py
headjack/config.py
headjack/embeddings.py
headjack-0.0.1a1.dist-info/LICENSE
headjack-0.0.1a1.dist-info/METADATA
headjack-0.0.1a1.dist-info/WHEEL
headjack-0.0.1a1.dist-info/RECORD
