Metadata-Version: 2.1
Name: headjack
Version: 0.0.1a1
Summary: 
Author: Nick Ouellet
Author-email: nicholas.p.ouellet@gmail.com
Requires-Python: >=3.10,<4.0
Classifier: Programming Language :: Python :: 3
Classifier: Programming Language :: Python :: 3.10
Classifier: Programming Language :: Python :: 3.11
Requires-Dist: chromadb (==0.3.21)
Requires-Dist: fastapi (>=0.71.0)
Requires-Dist: lmql (>=0.0.4.2)
